py24so/__init__.py
py24so-0.2.1.dist-info/licenses/LICENSE
py24so-0.2.1.dist-info/METADATA
py24so-0.2.1.dist-info/WHEEL
py24so-0.2.1.dist-info/top_level.txt
py24so-0.2.1.dist-info/RECORD
