Metadata-Version: 2.4
Name: py24so
Version: 0.2.1
Summary: Modern Python client for the 24SevenOffice API
Author-email: Sondre Dyrnes <sondre@villdyr.no>
Classifier: Programming Language :: Python :: 3
Classifier: License :: OSI Approved :: MIT License
Classifier: Operating System :: OS Independent
Requires-Python: >=3.9
License-File: LICENSE
Requires-Dist: httpx>=0.24.0
Requires-Dist: pydantic>=2.0.0
Requires-Dist: backoff>=2.2.1
Requires-Dist: tenacity>=8.2.2
Requires-Dist: hishel>=0.0.17
Requires-Dist: python-dotenv>=1.0.0
Requires-Dist: pytest-asyncio>=0.26.0
Requires-Dist: email-validator>=2.2.0
Provides-Extra: http2
Requires-Dist: httpx[http2]>=0.24.0; extra == "http2"
Provides-Extra: dev
Requires-Dist: pytest>=7.3.1; extra == "dev"
Requires-Dist: pytest-cov>=4.1.0; extra == "dev"
Requires-Dist: pytest-asyncio>=0.21.0; extra == "dev"
Requires-Dist: black>=23.3.0; extra == "dev"
Requires-Dist: isort>=5.12.0; extra == "dev"
Requires-Dist: mypy>=1.3.0; extra == "dev"
Dynamic: license-file
